<?xml version="1.0" encoding="UTF-8" standalone="no"?>
<root>
    <data>
        <demands>1350</demands>
        <priority>1107</priority>
        <best_effort>243</best_effort>
        <priority_percentage>0.5</priority_percentage>
        <single_transponder_for_all>false</single_transponder_for_all>
        <single_transponder_type>false</single_transponder_type>
        <number_ZR>1014</number_ZR>
        <number_LR>614</number_LR>
        <total_Cost>1121</total_Cost>
        <Transponder_Island1>116</Transponder_Island1>
        <Transponder_Island2>196</Transponder_Island2>
        <Transponder_Island3>320</Transponder_Island3>
        <Transponder_Island4>245</Transponder_Island4>
        <Transponder_Island5>73</Transponder_Island5>
        <Transponder_Island6>138</Transponder_Island6>
        <Transponder_Island7>305</Transponder_Island7>
        <Transponder_Island8>79</Transponder_Island8>
        <Transponder_Island9>156</Transponder_Island9>
    </data>
</root>
